groundwork/__init__.py
groundwork/exceptions.py
groundwork/groundwork.py
groundwork/pluginmanager.py
groundwork/signals.py
groundwork/util.py
groundwork/version.py
groundwork/applications/__init__.py
groundwork/applications/configuration.py
groundwork/applications/gw_base_app.py
groundwork/configuration/__init__.py
groundwork/configuration/config.py
groundwork/configuration/configmanager.py
groundwork/configuration/exceptions.py
groundwork/patterns/__init__.py
groundwork/patterns/exceptions.py
groundwork/patterns/gw_base_pattern.py
groundwork/patterns/gw_commands_pattern.py
groundwork/patterns/gw_documents_pattern.py
groundwork/patterns/gw_recipes_pattern.py
groundwork/patterns/gw_shared_objects_pattern.py
groundwork/patterns/gw_threads_pattern.py
groundwork/plugins/__init__.py
groundwork/plugins/gw_commands_info.py
groundwork/plugins/gw_documents_info.py
groundwork/plugins/gw_plugins_info.py
groundwork/plugins/gw_recipes_builder.py
groundwork/plugins/gw_signals_info.py
groundwork/recipes/__init__.py
groundwork/recipes/gw_package/cookiecutter.json
groundwork/recipes/gw_package/{{cookiecutter.project_name}}/.gitignore
groundwork/recipes/gw_package/{{cookiecutter.project_name}}/.travis.yml
groundwork/recipes/gw_package/{{cookiecutter.project_name}}/README
groundwork/recipes/gw_package/{{cookiecutter.project_name}}/bootstrap.py
groundwork/recipes/gw_package/{{cookiecutter.project_name}}/buildout.cfg
groundwork/recipes/gw_package/{{cookiecutter.project_name}}/doc-requirements.txt
groundwork/recipes/gw_package/{{cookiecutter.project_name}}/setup.py
groundwork/recipes/gw_package/{{cookiecutter.project_name}}/test-requirements.txt
groundwork/recipes/gw_package/{{cookiecutter.project_name}}/tox.ini
groundwork/recipes/gw_package/{{cookiecutter.project_name}}/versions.cfg
groundwork/recipes/gw_package/{{cookiecutter.project_name}}/docs/Makefile
groundwork/recipes/gw_package/{{cookiecutter.project_name}}/docs/conf.py
groundwork-0.1.13.dist-info/DESCRIPTION.rst
groundwork-0.1.13.dist-info/METADATA
groundwork-0.1.13.dist-info/RECORD
groundwork-0.1.13.dist-info/WHEEL
groundwork-0.1.13.dist-info/entry_points.txt
groundwork-0.1.13.dist-info/metadata.json
groundwork-0.1.13.dist-info/top_level.txt
