Metadata-Version: 2.0
Name: groundwork
Version: 0.1.13
Summary: A plugin-based microframework for highly reusable applications and their components
Home-page: http://groundwork.readthedocs.org
Author: team useblocks
Author-email: info@useblocks.com
License: MIT
Platform: any
Classifier: Development Status :: 3 - Alpha
Classifier: Environment :: Console
Classifier: Intended Audience :: Developers
Classifier: License :: OSI Approved :: MIT License
Classifier: Operating System :: OS Independent
Classifier: Programming Language :: Python
Classifier: Programming Language :: Python :: 2
Classifier: Programming Language :: Python :: 2.7
Classifier: Programming Language :: Python :: 3
Classifier: Programming Language :: Python :: 3.3
Classifier: Programming Language :: Python :: 3.4
Classifier: Programming Language :: Python :: 3.5
Classifier: Programming Language :: Python :: 3.6
Requires-Dist: pathlib
Requires-Dist: click
Requires-Dist: blinker
Requires-Dist: jinja2
Requires-Dist: cookiecutter
Requires-Dist: docutils
